reemote/__init__.py
reemote/app.py
reemote/apt.py
reemote/config.py
reemote/context.py
reemote/execute.py
reemote/host.py
reemote/inventory.py
reemote/module.py
reemote/scp.py
reemote/sftp.py
reemote/system.py
reemote/core/__init__.py
reemote/core/inventory_model.py
reemote/core/local.py
reemote/core/parse_apt_list_installed.py
reemote/core/remote.py
reemote/core/response.py
reemote/core/router_handler.py
reemote-0.1.3.dist-info/entry_points.txt
reemote-0.1.3.dist-info/licenses/LICENSE
reemote-0.1.3.dist-info/WHEEL
reemote-0.1.3.dist-info/METADATA
reemote-0.1.3.dist-info/RECORD
