Metadata-Version: 2.4
Name: reemote
Version: 0.1.3
Summary: An API for controlling remote systems.
Author-email: Kim Jarvis <kim.jarvis@tpfsystems.com>
Maintainer-email: Kim Jarvis <kim.jarvis@tpfsystems.com>
Requires-Python: >=3.13
License-Expression: MIT
License-File: LICENSE
Requires-Dist: asyncssh>=2.21.1
Requires-Dist: coverage>=7.13.0
Requires-Dist: fastapi[standard]>=0.123.5
Requires-Dist: mkdocs>=1.6.1
Requires-Dist: mkdocs-material>=9.7.1
Requires-Dist: pydantic>=2.12.5
Requires-Dist: pytest>=9.0.1
Requires-Dist: pytest-asyncio>=1.3.0
Requires-Dist: ruff>=0.14.9
Requires-Dist: uvicorn>=0.38.0
Project-URL: Bug Tracker, https://github.com/kimjarvis/reemote/issues
Project-URL: Documentation, https://reemote.org/redoc-static.html
Project-URL: Homepage, http://reemote.org/index.html
Project-URL: Source Code, https://github.com/kimjarvis/reemote
